cyforge/__init__.py
cyforge/block.py
cyforge/message.py
cyforge/blocks/__init__.py
cyforge/blocks/responder.py
cyforge/blocks/schema.py
cyforge/blocks/switch.py
cyforge/blocks/responders/__init__.py
cyforge/blocks/responders/countLedger.py
cyforge/blocks/responders/echo.py
cyforge/blocks/responders/machineModel.py
cyforge/blocks/responders/responseGenerator.py
cyforge/blocks/responders/textInput.py
cyforge/blocks/switches/__init__.py
cyforge-0.1.6.dist-info/licenses/LICENSE
cyforge-0.1.6.dist-info/METADATA
cyforge-0.1.6.dist-info/WHEEL
cyforge-0.1.6.dist-info/top_level.txt
cyforge-0.1.6.dist-info/RECORD
