Metadata-Version: 2.4
Name: cyforge
Version: 0.1.6
Summary: Coming soon
Author-email: Matt Hoffman <matthew@hoffmain.com>
License-File: LICENSE
Dynamic: license-file
